to7m_convenience/__init__.py
to7m_convenience/debugging.py
to7m_convenience/maths.py
to7m_convenience/simple_functions.py
to7m_convenience-0.0.0.dist-info/LICENSE
to7m_convenience-0.0.0.dist-info/LICENSE.TXT
to7m_convenience-0.0.0.dist-info/METADATA
to7m_convenience-0.0.0.dist-info/WHEEL
to7m_convenience-0.0.0.dist-info/top_level.txt
to7m_convenience-0.0.0.dist-info/RECORD
