Metadata-Version: 2.1
Name: to7m_convenience
Version: 0.0.0
Summary: Just a few general tools.
Home-page: https://gitlab.com/to7m/to7m_convenience.git
Author: to7m
Author-email: mail@to7m.lol
License: UNKNOWN
Platform: UNKNOWN
Classifier: Programming Language :: Python :: 3
Classifier: License :: OSI Approved :: GNU Affero General Public License v3
Classifier: Operating System :: POSIX :: Linux
Requires-Python: >=3.10
License-File: LICENSE
License-File: LICENSE.TXT
